dff.v
`timescale 1ns / 1ps

// Simple positive-edge triggered D flip-flop with asynchronous reset
module dff(
    input  wire clk,
    input  wire reset,
    input  wire d,
    output reg  q
);
    always @(posedge clk or posedge reset) begin
        if (reset)
            q <= 1'b0;
        else
            q <= d;
    end
endmodule

counter.v
`timescale 1ns / 1ps

// Counter implemented using D flip-flops (parameterized width)
module counter #(
    parameter WIDTH = 4
) (
    input  wire                 clk,
    input  wire                 reset,
    output wire [WIDTH-1:0]     q
);

    // Internal wires for D inputs
    wire [WIDTH-1:0] d;

    // Simple combinational logic for next-state (binary increment)
    // d = q + 1
    assign d = q + 1'b1;

    // Instantiate D flip-flops
    genvar gi;
    generate
        for (gi = 0; gi < WIDTH; gi = gi + 1) begin : DFFS
            dff u_dff (
                .clk(clk),
                .reset(reset),
                .d(d[gi]),
                .q(q[gi])
            );
        end
    endgenerate

    // No internal sequential copy needed: DFF outputs `q` hold the state

endmodule

tb_counter.v
`timescale 1ns / 1ps

// Self-checking testbench for the parameterized counter
module tb_counter;

    parameter WIDTH = 4;
    localparam MAX_COUNT = (1<<WIDTH);

    reg clk = 0;
    reg reset;
    wire [WIDTH-1:0] q;

    // Device under test
    counter #(.WIDTH(WIDTH)) dut (
        .clk(clk),
        .reset(reset),
        .q(q)
    );

    // Clock: 10 ns period
    always #5 clk = ~clk;

    // VCD dump
    initial begin
        $dumpfile("counter_waveform.vcd");
        $dumpvars(0, tb_counter);
    end

    // Self-checking sequence
    integer i;
    reg error;
    reg [WIDTH-1:0] expected;

    initial begin
        // Initialize
        error = 0;
        expected = 0;
        reset = 1;

        // Hold reset for a bit > one clock edge
        #12;
        @(negedge clk);
        reset = 0; // release reset

        // Allow a few clock cycles and check sequence
        for (i = 0; i < (MAX_COUNT + 4); i = i + 1) begin
            @(posedge clk);
            #1; // wait for signals to settle
            // The counter increments on the posedge, so advance expected first
            expected = expected + 1'b1;
            $display("Time %0t: q = %0d (expected %0d)", $time, q, expected);
            if (q !== expected) begin
                $display("ERROR at time %0t: q=%0d expected=%0d", $time, q, expected);
                error = 1;
            end
        end

        if (!error) begin
            $display("\nTEST PASSED: Counter incremented correctly for %0d cycles", i);
        end else begin
            $display("\nTEST FAILED: See ERROR messages above");
        end

        // Give time for dump then finish
        #5;
        $finish;
    end

endmodule

counter_waveform.vcd
$date
	Fri Oct 03 23:32:44 2025
$end
$version
	Icarus Verilog
$end
$timescale
	1ps
$end
$scope module tb_counter $end
$var wire 4 ! q [3:0] $end
$var parameter 36 " MAX_COUNT $end
$var parameter 32 # WIDTH $end
$var reg 1 $ clk $end
$var reg 1 % error $end
$var reg 4 & expected [3:0] $end
$var reg 1 ' reset $end
$var integer 32 ( i [31:0] $end
$scope module dut $end
$var wire 1 $ clk $end
$var wire 1 ' reset $end
$var wire 4 ) q [3:0] $end
$var wire 4 * d [3:0] $end
$var parameter 32 + WIDTH $end
$scope begin DFFS[0] $end
$var parameter 2 , gi $end
$scope module u_dff $end
$var wire 1 $ clk $end
$var wire 1 - d $end
$var wire 1 ' reset $end
$var reg 1 . q $end
$upscope $end
$upscope $end
$scope begin DFFS[1] $end
$var parameter 2 / gi $end
$scope module u_dff $end
$var wire 1 $ clk $end
$var wire 1 0 d $end
$var wire 1 ' reset $end
$var reg 1 1 q $end
$upscope $end
$upscope $end
$scope begin DFFS[2] $end
$var parameter 3 2 gi $end
$scope module u_dff $end
$var wire 1 $ clk $end
$var wire 1 3 d $end
$var wire 1 ' reset $end
$var reg 1 4 q $end
$upscope $end
$upscope $end
$scope begin DFFS[3] $end
$var parameter 3 5 gi $end
$scope module u_dff $end
$var wire 1 $ clk $end
$var wire 1 6 d $end
$var wire 1 ' reset $end
$var reg 1 7 q $end
$upscope $end
$upscope $end
$upscope $end
$upscope $end
$enddefinitions $end
$comment Show the parameter values. $end
$dumpall
b11 5
b10 2
b1 /
b0 ,
b100 +
b100 #
b10000 "
$end
#0
$dumpvars
07
06
04
03
01
00
0.
1-
b1 *
b0 )
bx (
1'
b0 &
0%
0$
b0 !
$end
#5000
1$
#10000
0$
#15000
1$
#20000
b0 (
0'
0$
#25000
10
0-
b10 *
b1 !
b1 )
1.
1$
#26000
b1 (
b1 &
#30000
0$
#35000
1-
0.
b11 *
b10 !
b10 )
11
1$
#36000
b10 (
b10 &
#40000
0$
#45000
13
00
0-
b100 *
b11 !
b11 )
1.
1$
#46000
b11 (
b11 &
#50000
0$
#55000
1-
0.
01
b101 *
b100 !
b100 )
14
1$
#56000
b100 (
b100 &
#60000
0$
#65000
10
0-
b110 *
b101 !
b101 )
1.
1$
#66000
b101 (
b101 &
#70000
0$
#75000
1-
0.
b111 *
b110 !
b110 )
11
1$
#76000
b110 (
b110 &
#80000
0$
#85000
16
03
00
0-
b1000 *
b111 !
b111 )
1.
1$
#86000
b111 (
b111 &
#90000
0$
#95000
1-
0.
01
04
b1001 *
b1000 !
b1000 )
17
1$
#96000
b1000 (
b1000 &
#100000
0$
#105000
10
0-
b1010 *
b1001 !
b1001 )
1.
1$
#106000
b1001 (
b1001 &
#110000
0$
#115000
1-
0.
b1011 *
b1010 !
b1010 )
11
1$
#116000
b1010 (
b1010 &
#120000
0$
#125000
13
00
0-
b1100 *
b1011 !
b1011 )
1.
1$
#126000
b1011 (
b1011 &
#130000
0$
#135000
1-
0.
01
b1101 *
b1100 !
b1100 )
14
1$
#136000
b1100 (
b1100 &
#140000
0$
#145000
10
0-
b1110 *
b1101 !
b1101 )
1.
1$
#146000
b1101 (
b1101 &
#150000
0$
#155000
1-
0.
b1111 *
b1110 !
b1110 )
11
1$
#156000
b1110 (
b1110 &
#160000
0$
#165000
06
03
00
0-
b0 *
b1111 !
b1111 )
1.
1$
#166000
b1111 (
b1111 &
#170000
0$
#175000
1-
0.
01
04
b1 *
b0 !
b0 )
07
1$
#176000
b10000 (
b0 &
#180000
0$
#185000
10
0-
b10 *
b1 !
b1 )
1.
1$
#186000
b10001 (
b1 &
#190000
0$
#195000
1-
0.
b11 *
b10 !
b10 )
11
1$
#196000
b10010 (
b10 &
#200000
0$
#205000
13
00
0-
b100 *
b11 !
b11 )
1.
1$
#206000
b10011 (
b11 &
#210000
0$
#215000
1-
0.
01
b101 *
b100 !
b100 )
14
1$
#216000
b10100 (
b100 &
